{
  "field" : "rootTwo",
  "symmetry" : "octahedral",
  "orientations" : [ [ 1.0, 0.0, 0.0, 0.0, 0.0, 1.0, 0.0, 0.0, 0.0, 0.0, 1.0, 0.0, 0.0, 0.0, 0.0, 1.0 ], [ 1.0, 0.0, 0.0, 0.0, 0.0, 0.0, 1.0, 0.0, 0.0, -1.0, 0.0, 0.0, 0.0, 0.0, 0.0, 1.0 ], [ 1.0, 0.0, 0.0, 0.0, 0.0, -1.0, 0.0, 0.0, 0.0, 0.0, -1.0, 0.0, 0.0, 0.0, 0.0, 1.0 ], [ 1.0, 0.0, 0.0, 0.0, 0.0, 0.0, -1.0, 0.0, 0.0, 1.0, 0.0, 0.0, 0.0, 0.0, 0.0, 1.0 ], [ 0.0, 1.0, 0.0, 0.0, 0.0, 0.0, 1.0, 0.0, 1.0, 0.0, 0.0, 0.0, 0.0, 0.0, 0.0, 1.0 ], [ 0.0, 1.0, 0.0, 0.0, 1.0, 0.0, 0.0, 0.0, 0.0, 0.0, -1.0, 0.0, 0.0, 0.0, 0.0, 1.0 ], [ 0.0, 1.0, 0.0, 0.0, 0.0, 0.0, -1.0, 0.0, -1.0, 0.0, 0.0, 0.0, 0.0, 0.0, 0.0, 1.0 ], [ 0.0, 1.0, 0.0, 0.0, -1.0, 0.0, 0.0, 0.0, 0.0, 0.0, 1.0, 0.0, 0.0, 0.0, 0.0, 1.0 ], [ 0.0, 0.0, 1.0, 0.0, 1.0, 0.0, 0.0, 0.0, 0.0, 1.0, 0.0, 0.0, 0.0, 0.0, 0.0, 1.0 ], [ 0.0, 0.0, 1.0, 0.0, 0.0, 1.0, 0.0, 0.0, -1.0, 0.0, 0.0, 0.0, 0.0, 0.0, 0.0, 1.0 ], [ 0.0, 0.0, 1.0, 0.0, -1.0, 0.0, 0.0, 0.0, 0.0, -1.0, 0.0, 0.0, 0.0, 0.0, 0.0, 1.0 ], [ 0.0, 0.0, 1.0, 0.0, 0.0, -1.0, 0.0, 0.0, 1.0, 0.0, 0.0, 0.0, 0.0, 0.0, 0.0, 1.0 ], [ -1.0, 0.0, 0.0, 0.0, 0.0, -1.0, 0.0, 0.0, 0.0, 0.0, 1.0, 0.0, 0.0, 0.0, 0.0, 1.0 ], [ -1.0, 0.0, 0.0, 0.0, 0.0, 0.0, 1.0, 0.0, 0.0, 1.0, 0.0, 0.0, 0.0, 0.0, 0.0, 1.0 ], [ -1.0, 0.0, 0.0, 0.0, 0.0, 1.0, 0.0, 0.0, 0.0, 0.0, -1.0, 0.0, 0.0, 0.0, 0.0, 1.0 ], [ -1.0, 0.0, 0.0, 0.0, 0.0, 0.0, -1.0, 0.0, 0.0, -1.0, 0.0, 0.0, 0.0, 0.0, 0.0, 1.0 ], [ 0.0, -1.0, 0.0, 0.0, 0.0, 0.0, -1.0, 0.0, 1.0, 0.0, 0.0, 0.0, 0.0, 0.0, 0.0, 1.0 ], [ 0.0, -1.0, 0.0, 0.0, 1.0, 0.0, 0.0, 0.0, 0.0, 0.0, 1.0, 0.0, 0.0, 0.0, 0.0, 1.0 ], [ 0.0, -1.0, 0.0, 0.0, 0.0, 0.0, 1.0, 0.0, -1.0, 0.0, 0.0, 0.0, 0.0, 0.0, 0.0, 1.0 ], [ 0.0, -1.0, 0.0, 0.0, -1.0, 0.0, 0.0, 0.0, 0.0, 0.0, -1.0, 0.0, 0.0, 0.0, 0.0, 1.0 ], [ 0.0, 0.0, -1.0, 0.0, -1.0, 0.0, 0.0, 0.0, 0.0, 1.0, 0.0, 0.0, 0.0, 0.0, 0.0, 1.0 ], [ 0.0, 0.0, -1.0, 0.0, 0.0, 1.0, 0.0, 0.0, 1.0, 0.0, 0.0, 0.0, 0.0, 0.0, 0.0, 1.0 ], [ 0.0, 0.0, -1.0, 0.0, 1.0, 0.0, 0.0, 0.0, 0.0, -1.0, 0.0, 0.0, 0.0, 0.0, 0.0, 1.0 ], [ 0.0, 0.0, -1.0, 0.0, 0.0, -1.0, 0.0, 0.0, -1.0, 0.0, 0.0, 0.0, 0.0, 0.0, 0.0, 1.0 ] ],
  "lights" : {
    "ambientColor" : "#292929",
    "backgroundColor" : "#B2CDE6",
    "directionalLights" : [ {
      "direction" : {
        "x" : 1.0,
        "y" : -1.0,
        "z" : -1.0
      },
      "color" : "#EBEBE4"
    }, {
      "direction" : {
        "x" : -1.0,
        "y" : 0.0,
        "z" : 0.0
      },
      "color" : "#E4E4EB"
    }, {
      "direction" : {
        "x" : 0.0,
        "y" : 0.0,
        "z" : -1.0
      },
      "color" : "#1E1E1E"
    } ]
  },
  "camera" : {
    "width" : 228.23413,
    "stereo" : false,
    "lookDirection" : {
      "x" : -0.27150437,
      "y" : 0.414872,
      "z" : -0.8684264
    },
    "upDirection" : {
      "x" : -0.27246282,
      "y" : 0.8322754,
      "z" : 0.4827845
    },
    "lookAtPoint" : {
      "x" : 19.31371,
      "y" : 0.0,
      "z" : -4.0
    },
    "viewDistance" : 507.18683,
    "nearClipDistance" : 1.2679689,
    "farClipDistance" : 1014.37665,
    "fieldOfView" : 0.44262898,
    "perspective" : true,
    "position" : {
      "x" : 157.01715,
      "y" : -210.4176,
      "z" : 436.45444
    }
  },
  "embedding" : [ 1.0, 0.0, 0.0, 0.0, 0.0, 1.0, 0.0, 0.0, 0.0, 0.0, 1.0, 0.0, 0.0, 0.0, 0.0, 1.0 ],
  "shapes" : [ {
    "id" : "fb1507dd-ee38-4bf9-9c09-b1ecd025d785",
    "vertices" : [ {
      "x" : 0.25,
      "y" : 0.25,
      "z" : -0.75
    }, {
      "x" : 0.25,
      "y" : -0.25,
      "z" : -0.75
    }, {
      "x" : -0.25,
      "y" : -0.25,
      "z" : -0.75
    }, {
      "x" : -0.25,
      "y" : 0.25,
      "z" : -0.75
    }, {
      "x" : -0.25,
      "y" : -0.75,
      "z" : -0.25
    }, {
      "x" : -0.75,
      "y" : -0.25,
      "z" : -0.25
    }, {
      "x" : 0.75,
      "y" : -0.25,
      "z" : -0.25
    }, {
      "x" : 0.25,
      "y" : -0.75,
      "z" : -0.25
    }, {
      "x" : 0.25,
      "y" : -0.25,
      "z" : 0.75
    }, {
      "x" : 0.25,
      "y" : 0.25,
      "z" : 0.75
    }, {
      "x" : -0.25,
      "y" : 0.25,
      "z" : 0.75
    }, {
      "x" : -0.25,
      "y" : -0.25,
      "z" : 0.75
    }, {
      "x" : 0.75,
      "y" : 0.25,
      "z" : 0.25
    }, {
      "x" : 0.25,
      "y" : 0.75,
      "z" : 0.25
    }, {
      "x" : -0.25,
      "y" : -0.75,
      "z" : 0.25
    }, {
      "x" : -0.75,
      "y" : -0.25,
      "z" : 0.25
    }, {
      "x" : 0.25,
      "y" : -0.75,
      "z" : 0.25
    }, {
      "x" : -0.75,
      "y" : 0.25,
      "z" : 0.25
    }, {
      "x" : -0.25,
      "y" : 0.75,
      "z" : 0.25
    }, {
      "x" : -0.25,
      "y" : 0.75,
      "z" : -0.25
    }, {
      "x" : -0.75,
      "y" : 0.25,
      "z" : -0.25
    }, {
      "x" : 0.25,
      "y" : 0.75,
      "z" : -0.25
    }, {
      "x" : 0.75,
      "y" : -0.25,
      "z" : 0.25
    }, {
      "x" : 0.75,
      "y" : 0.25,
      "z" : -0.25
    } ],
    "faces" : [ {
      "vertices" : [ 12, 23, 21 ]
    }, {
      "vertices" : [ 12, 21, 13 ]
    }, {
      "vertices" : [ 0, 1, 2 ]
    }, {
      "vertices" : [ 0, 2, 3 ]
    }, {
      "vertices" : [ 13, 21, 19 ]
    }, {
      "vertices" : [ 13, 19, 18 ]
    }, {
      "vertices" : [ 17, 18, 19 ]
    }, {
      "vertices" : [ 17, 19, 20 ]
    }, {
      "vertices" : [ 2, 4, 5 ]
    }, {
      "vertices" : [ 1, 6, 7 ]
    }, {
      "vertices" : [ 1, 7, 4 ]
    }, {
      "vertices" : [ 1, 4, 2 ]
    }, {
      "vertices" : [ 0, 23, 6 ]
    }, {
      "vertices" : [ 0, 6, 1 ]
    }, {
      "vertices" : [ 2, 5, 20 ]
    }, {
      "vertices" : [ 2, 20, 3 ]
    }, {
      "vertices" : [ 9, 12, 13 ]
    }, {
      "vertices" : [ 8, 9, 10 ]
    }, {
      "vertices" : [ 8, 10, 11 ]
    }, {
      "vertices" : [ 4, 14, 15 ]
    }, {
      "vertices" : [ 4, 15, 5 ]
    }, {
      "vertices" : [ 11, 15, 14 ]
    }, {
      "vertices" : [ 4, 7, 16 ]
    }, {
      "vertices" : [ 4, 16, 14 ]
    }, {
      "vertices" : [ 3, 20, 19 ]
    }, {
      "vertices" : [ 0, 3, 19 ]
    }, {
      "vertices" : [ 0, 19, 21 ]
    }, {
      "vertices" : [ 0, 21, 23 ]
    }, {
      "vertices" : [ 10, 18, 17 ]
    }, {
      "vertices" : [ 8, 16, 22 ]
    }, {
      "vertices" : [ 8, 11, 14 ]
    }, {
      "vertices" : [ 8, 14, 16 ]
    }, {
      "vertices" : [ 9, 13, 18 ]
    }, {
      "vertices" : [ 9, 18, 10 ]
    }, {
      "vertices" : [ 6, 22, 16 ]
    }, {
      "vertices" : [ 6, 16, 7 ]
    }, {
      "vertices" : [ 8, 22, 12 ]
    }, {
      "vertices" : [ 8, 12, 9 ]
    }, {
      "vertices" : [ 10, 17, 15 ]
    }, {
      "vertices" : [ 10, 15, 11 ]
    }, {
      "vertices" : [ 5, 15, 17 ]
    }, {
      "vertices" : [ 5, 17, 20 ]
    }, {
      "vertices" : [ 6, 23, 12 ]
    }, {
      "vertices" : [ 6, 12, 22 ]
    } ]
  }, {
    "id" : "4c9597d6-30d9-4032-beef-c8b010f6a888",
    "vertices" : [ {
      "x" : -13.270439,
      "y" : 5.6025147,
      "z" : -13.003773
    }, {
      "x" : -13.37044,
      "y" : 5.202515,
      "z" : -13.103772
    }, {
      "x" : -0.38641518,
      "y" : 0.05433931,
      "z" : -0.65308183
    }, {
      "x" : -0.28641516,
      "y" : 0.4543393,
      "z" : -0.5530818
    }, {
      "x" : -13.137106,
      "y" : 5.3358483,
      "z" : -13.403772
    }, {
      "x" : -13.037106,
      "y" : 5.7358484,
      "z" : -13.303772
    }, {
      "x" : -0.5197485,
      "y" : 0.32100597,
      "z" : -0.25308183
    }, {
      "x" : -0.61974853,
      "y" : -0.07899402,
      "z" : -0.35308185
    } ],
    "faces" : [ {
      "vertices" : [ 2, 3, 6 ]
    }, {
      "vertices" : [ 2, 6, 7 ]
    }, {
      "vertices" : [ 0, 5, 4 ]
    }, {
      "vertices" : [ 0, 4, 1 ]
    }, {
      "vertices" : [ 2, 4, 5 ]
    }, {
      "vertices" : [ 2, 5, 3 ]
    }, {
      "vertices" : [ 0, 6, 3 ]
    }, {
      "vertices" : [ 0, 3, 5 ]
    }, {
      "vertices" : [ 0, 1, 7 ]
    }, {
      "vertices" : [ 0, 7, 6 ]
    }, {
      "vertices" : [ 1, 4, 2 ]
    }, {
      "vertices" : [ 1, 2, 7 ]
    } ]
  }, {
    "id" : "21f47278-1ceb-4c52-b67f-5b959da5e322",
    "vertices" : [ {
      "x" : 12.906855,
      "y" : -0.25,
      "z" : 13.406855
    }, {
      "x" : 0.75,
      "y" : 0.25,
      "z" : 0.25
    }, {
      "x" : 0.25,
      "y" : 0.25,
      "z" : 0.75
    }, {
      "x" : 12.906855,
      "y" : 0.25,
      "z" : 13.406855
    }, {
      "x" : 13.406855,
      "y" : 0.25,
      "z" : 12.906855
    }, {
      "x" : 13.656855,
      "y" : 0.0,
      "z" : 13.656855
    }, {
      "x" : 0.75,
      "y" : -0.25,
      "z" : 0.25
    }, {
      "x" : 13.406855,
      "y" : -0.25,
      "z" : 12.906855
    }, {
      "x" : 0.25,
      "y" : -0.25,
      "z" : 0.75
    } ],
    "faces" : [ {
      "vertices" : [ 1, 4, 7 ]
    }, {
      "vertices" : [ 1, 7, 6 ]
    }, {
      "vertices" : [ 0, 8, 6 ]
    }, {
      "vertices" : [ 0, 6, 7 ]
    }, {
      "vertices" : [ 1, 2, 3 ]
    }, {
      "vertices" : [ 1, 3, 4 ]
    }, {
      "vertices" : [ 0, 3, 2 ]
    }, {
      "vertices" : [ 0, 2, 8 ]
    } ]
  }, {
    "id" : "87af3d82-ce02-46c4-9e55-c23a4bd5d149",
    "vertices" : [ {
      "x" : -13.157836,
      "y" : -5.22254,
      "z" : -5.555873
    }, {
      "x" : -13.257835,
      "y" : -5.32254,
      "z" : -5.155873
    }, {
      "x" : -0.49901876,
      "y" : -0.43431458,
      "z" : -0.10098124
    }, {
      "x" : -0.39901876,
      "y" : -0.33431458,
      "z" : -0.5009813
    }, {
      "x" : -13.024502,
      "y" : -5.6225395,
      "z" : -5.2892065
    }, {
      "x" : -12.924502,
      "y" : -5.5225396,
      "z" : -5.689206
    }, {
      "x" : -0.6323521,
      "y" : -0.034314577,
      "z" : -0.36764792
    }, {
      "x" : -0.7323521,
      "y" : -0.13431458,
      "z" : 0.03235209
    } ],
    "faces" : [ {
      "vertices" : [ 2, 3, 6 ]
    }, {
      "vertices" : [ 2, 6, 7 ]
    }, {
      "vertices" : [ 0, 5, 4 ]
    }, {
      "vertices" : [ 0, 4, 1 ]
    }, {
      "vertices" : [ 2, 4, 5 ]
    }, {
      "vertices" : [ 2, 5, 3 ]
    }, {
      "vertices" : [ 0, 6, 3 ]
    }, {
      "vertices" : [ 0, 3, 5 ]
    }, {
      "vertices" : [ 0, 1, 7 ]
    }, {
      "vertices" : [ 0, 7, 6 ]
    }, {
      "vertices" : [ 1, 4, 2 ]
    }, {
      "vertices" : [ 1, 2, 7 ]
    } ]
  }, {
    "id" : "7e88e7b3-3737-44bb-8ee6-72e2ff7736b2",
    "vertices" : [ {
      "x" : -13.082767,
      "y" : 5.191445,
      "z" : 0.13333334
    }, {
      "x" : -13.182766,
      "y" : 5.2914453,
      "z" : -0.26666668
    }, {
      "x" : -0.5740878,
      "y" : 0.4654092,
      "z" : -0.13333334
    }, {
      "x" : -0.4740878,
      "y" : 0.3654092,
      "z" : 0.26666668
    }, {
      "x" : -12.949433,
      "y" : 5.591445,
      "z" : -0.13333334
    }, {
      "x" : -12.849433,
      "y" : 5.491445,
      "z" : 0.26666668
    }, {
      "x" : -0.7074211,
      "y" : 0.0654092,
      "z" : 0.13333334
    }, {
      "x" : -0.80742115,
      "y" : 0.16540919,
      "z" : -0.26666668
    } ],
    "faces" : [ {
      "vertices" : [ 2, 3, 6 ]
    }, {
      "vertices" : [ 2, 6, 7 ]
    }, {
      "vertices" : [ 0, 5, 4 ]
    }, {
      "vertices" : [ 0, 4, 1 ]
    }, {
      "vertices" : [ 2, 4, 5 ]
    }, {
      "vertices" : [ 2, 5, 3 ]
    }, {
      "vertices" : [ 0, 6, 3 ]
    }, {
      "vertices" : [ 0, 3, 5 ]
    }, {
      "vertices" : [ 0, 1, 7 ]
    }, {
      "vertices" : [ 0, 7, 6 ]
    }, {
      "vertices" : [ 1, 4, 2 ]
    }, {
      "vertices" : [ 1, 2, 7 ]
    } ]
  }, {
    "id" : "0a7b0236-3b72-4ad6-be57-4a2253ea6315",
    "vertices" : [ {
      "x" : 7.604973,
      "y" : -0.26666668,
      "z" : -5.159677
    }, {
      "x" : 7.504973,
      "y" : 0.13333334,
      "z" : -5.059677
    }, {
      "x" : 0.39502692,
      "y" : 0.26666668,
      "z" : -0.49717733
    }, {
      "x" : 0.49502692,
      "y" : -0.13333334,
      "z" : -0.5971773
    }, {
      "x" : 7.27164,
      "y" : 0.26666668,
      "z" : -5.359677
    }, {
      "x" : 7.3716397,
      "y" : -0.13333334,
      "z" : -5.4596767
    }, {
      "x" : 0.72836024,
      "y" : -0.26666668,
      "z" : -0.29717734
    }, {
      "x" : 0.6283603,
      "y" : 0.13333334,
      "z" : -0.19717735
    } ],
    "faces" : [ {
      "vertices" : [ 2, 3, 6 ]
    }, {
      "vertices" : [ 2, 6, 7 ]
    }, {
      "vertices" : [ 0, 5, 4 ]
    }, {
      "vertices" : [ 0, 4, 1 ]
    }, {
      "vertices" : [ 2, 4, 5 ]
    }, {
      "vertices" : [ 2, 5, 3 ]
    }, {
      "vertices" : [ 0, 6, 3 ]
    }, {
      "vertices" : [ 0, 3, 5 ]
    }, {
      "vertices" : [ 0, 1, 7 ]
    }, {
      "vertices" : [ 0, 7, 6 ]
    }, {
      "vertices" : [ 1, 4, 2 ]
    }, {
      "vertices" : [ 1, 2, 7 ]
    } ]
  }, {
    "id" : "99d39fe5-0c6b-44dc-9054-22d0a2f9b241",
    "vertices" : [ {
      "x" : -7.5532455,
      "y" : -0.26666668,
      "z" : -13.231574
    }, {
      "x" : -7.453245,
      "y" : 0.13333334,
      "z" : -13.131574
    }, {
      "x" : -0.44675463,
      "y" : 0.26666668,
      "z" : -0.42528054
    }, {
      "x" : -0.54675466,
      "y" : -0.13333334,
      "z" : -0.52528054
    }, {
      "x" : -7.7532454,
      "y" : 0.26666668,
      "z" : -12.89824
    }, {
      "x" : -7.8532453,
      "y" : -0.13333334,
      "z" : -12.99824
    }, {
      "x" : -0.24675465,
      "y" : -0.26666668,
      "z" : -0.7586139
    }, {
      "x" : -0.14675465,
      "y" : 0.13333334,
      "z" : -0.65861386
    } ],
    "faces" : [ {
      "vertices" : [ 2, 3, 6 ]
    }, {
      "vertices" : [ 2, 6, 7 ]
    }, {
      "vertices" : [ 0, 5, 4 ]
    }, {
      "vertices" : [ 0, 4, 1 ]
    }, {
      "vertices" : [ 2, 4, 5 ]
    }, {
      "vertices" : [ 2, 5, 3 ]
    }, {
      "vertices" : [ 0, 6, 3 ]
    }, {
      "vertices" : [ 0, 3, 5 ]
    }, {
      "vertices" : [ 0, 1, 7 ]
    }, {
      "vertices" : [ 0, 7, 6 ]
    }, {
      "vertices" : [ 1, 4, 2 ]
    }, {
      "vertices" : [ 1, 2, 7 ]
    } ]
  }, {
    "id" : "d4858e14-52d5-42eb-a50e-9361c57d7ebd",
    "vertices" : [ {
      "x" : 18.918682,
      "y" : -0.26666668,
      "z" : -13.159677
    }, {
      "x" : 18.818682,
      "y" : 0.13333334,
      "z" : -13.059677
    }, {
      "x" : 0.39502692,
      "y" : 0.26666668,
      "z" : -0.49717733
    }, {
      "x" : 0.49502692,
      "y" : -0.13333334,
      "z" : -0.5971773
    }, {
      "x" : 18.585348,
      "y" : 0.26666668,
      "z" : -13.359677
    }, {
      "x" : 18.685349,
      "y" : -0.13333334,
      "z" : -13.459677
    }, {
      "x" : 0.72836024,
      "y" : -0.26666668,
      "z" : -0.29717734
    }, {
      "x" : 0.6283603,
      "y" : 0.13333334,
      "z" : -0.19717735
    } ],
    "faces" : [ {
      "vertices" : [ 2, 3, 6 ]
    }, {
      "vertices" : [ 2, 6, 7 ]
    }, {
      "vertices" : [ 0, 5, 4 ]
    }, {
      "vertices" : [ 0, 4, 1 ]
    }, {
      "vertices" : [ 2, 4, 5 ]
    }, {
      "vertices" : [ 2, 5, 3 ]
    }, {
      "vertices" : [ 0, 6, 3 ]
    }, {
      "vertices" : [ 0, 3, 5 ]
    }, {
      "vertices" : [ 0, 1, 7 ]
    }, {
      "vertices" : [ 0, 7, 6 ]
    }, {
      "vertices" : [ 1, 4, 2 ]
    }, {
      "vertices" : [ 1, 2, 7 ]
    } ]
  }, {
    "id" : "02d2ab73-f5b6-4324-9d2d-c9907fb04a62",
    "vertices" : [ {
      "x" : 3.25,
      "y" : -0.25,
      "z" : 3.75
    }, {
      "x" : 0.75,
      "y" : 0.25,
      "z" : 0.25
    }, {
      "x" : 0.25,
      "y" : 0.25,
      "z" : 0.75
    }, {
      "x" : 3.25,
      "y" : 0.25,
      "z" : 3.75
    }, {
      "x" : 3.75,
      "y" : 0.25,
      "z" : 3.25
    }, {
      "x" : 4.0,
      "y" : 0.0,
      "z" : 4.0
    }, {
      "x" : 0.75,
      "y" : -0.25,
      "z" : 0.25
    }, {
      "x" : 3.75,
      "y" : -0.25,
      "z" : 3.25
    }, {
      "x" : 0.25,
      "y" : -0.25,
      "z" : 0.75
    } ],
    "faces" : [ {
      "vertices" : [ 1, 4, 7 ]
    }, {
      "vertices" : [ 1, 7, 6 ]
    }, {
      "vertices" : [ 0, 8, 6 ]
    }, {
      "vertices" : [ 0, 6, 7 ]
    }, {
      "vertices" : [ 1, 2, 3 ]
    }, {
      "vertices" : [ 1, 3, 4 ]
    }, {
      "vertices" : [ 0, 3, 2 ]
    }, {
      "vertices" : [ 0, 2, 8 ]
    } ]
  }, {
    "id" : "f8b4c7ca-148d-4a72-9d06-6ad5e5177196",
    "vertices" : [ {
      "x" : 4.906854,
      "y" : -0.25,
      "z" : 5.406854
    }, {
      "x" : 0.75,
      "y" : 0.25,
      "z" : 0.25
    }, {
      "x" : 0.25,
      "y" : 0.25,
      "z" : 0.75
    }, {
      "x" : 4.906854,
      "y" : 0.25,
      "z" : 5.406854
    }, {
      "x" : 5.406854,
      "y" : 0.25,
      "z" : 4.906854
    }, {
      "x" : 5.656854,
      "y" : 0.0,
      "z" : 5.656854
    }, {
      "x" : 0.75,
      "y" : -0.25,
      "z" : 0.25
    }, {
      "x" : 5.406854,
      "y" : -0.25,
      "z" : 4.906854
    }, {
      "x" : 0.25,
      "y" : -0.25,
      "z" : 0.75
    } ],
    "faces" : [ {
      "vertices" : [ 1, 4, 7 ]
    }, {
      "vertices" : [ 1, 7, 6 ]
    }, {
      "vertices" : [ 0, 8, 6 ]
    }, {
      "vertices" : [ 0, 6, 7 ]
    }, {
      "vertices" : [ 1, 2, 3 ]
    }, {
      "vertices" : [ 1, 3, 4 ]
    }, {
      "vertices" : [ 0, 3, 2 ]
    }, {
      "vertices" : [ 0, 2, 8 ]
    } ]
  }, {
    "id" : "5b4381aa-fcb4-4876-9af1-ead25f48c954",
    "vertices" : [ {
      "x" : -12.686292,
      "y" : 51.31371,
      "z" : 24.0
    }, {
      "x" : -12.686292,
      "y" : 51.31371,
      "z" : -40.0
    }, {
      "x" : 51.31371,
      "y" : 51.31371,
      "z" : -40.0
    }, {
      "x" : 51.31371,
      "y" : 51.31371,
      "z" : 24.0
    } ],
    "faces" : [ {
      "vertices" : [ 0, 1, 2 ]
    }, {
      "vertices" : [ 0, 2, 3 ]
    }, {
      "vertices" : [ 0, 3, 2 ]
    }, {
      "vertices" : [ 0, 2, 1 ]
    } ]
  }, {
    "id" : "36332ae0-e70e-4216-b55f-7cc0c49bb5dd",
    "vertices" : [ {
      "x" : 40.906853,
      "y" : -0.25,
      "z" : 41.406853
    }, {
      "x" : 0.75,
      "y" : 0.25,
      "z" : 0.25
    }, {
      "x" : 0.25,
      "y" : 0.25,
      "z" : 0.75
    }, {
      "x" : 40.906853,
      "y" : 0.25,
      "z" : 41.406853
    }, {
      "x" : 41.406853,
      "y" : 0.25,
      "z" : 40.906853
    }, {
      "x" : 41.656853,
      "y" : 0.0,
      "z" : 41.656853
    }, {
      "x" : 0.75,
      "y" : -0.25,
      "z" : 0.25
    }, {
      "x" : 41.406853,
      "y" : -0.25,
      "z" : 40.906853
    }, {
      "x" : 0.25,
      "y" : -0.25,
      "z" : 0.75
    } ],
    "faces" : [ {
      "vertices" : [ 1, 4, 7 ]
    }, {
      "vertices" : [ 1, 7, 6 ]
    }, {
      "vertices" : [ 0, 8, 6 ]
    }, {
      "vertices" : [ 0, 6, 7 ]
    }, {
      "vertices" : [ 1, 2, 3 ]
    }, {
      "vertices" : [ 1, 3, 4 ]
    }, {
      "vertices" : [ 0, 3, 2 ]
    }, {
      "vertices" : [ 0, 2, 8 ]
    } ]
  }, {
    "id" : "463a63cf-d01b-440e-8047-c3b6ca4c797f",
    "vertices" : [ {
      "x" : 51.31371,
      "y" : 51.31371,
      "z" : 24.0
    }, {
      "x" : 51.31371,
      "y" : 51.31371,
      "z" : -40.0
    }, {
      "x" : 115.313705,
      "y" : 51.31371,
      "z" : -40.0
    }, {
      "x" : 115.313705,
      "y" : 51.31371,
      "z" : 24.0
    } ],
    "faces" : [ {
      "vertices" : [ 0, 1, 2 ]
    }, {
      "vertices" : [ 0, 2, 3 ]
    }, {
      "vertices" : [ 0, 3, 2 ]
    }, {
      "vertices" : [ 0, 2, 1 ]
    } ]
  }, {
    "id" : "959261da-01ae-4197-8924-efd62286e939",
    "vertices" : [ {
      "x" : -32.0,
      "y" : -32.0,
      "z" : 32.0
    }, {
      "x" : -32.0,
      "y" : -32.0,
      "z" : -32.0
    }, {
      "x" : -32.0,
      "y" : 32.0,
      "z" : -32.0
    }, {
      "x" : -32.0,
      "y" : 32.0,
      "z" : 32.0
    } ],
    "faces" : [ {
      "vertices" : [ 0, 1, 2 ]
    }, {
      "vertices" : [ 0, 2, 3 ]
    }, {
      "vertices" : [ 0, 3, 2 ]
    }, {
      "vertices" : [ 0, 2, 1 ]
    } ]
  }, {
    "id" : "ff7d2686-8608-4e47-890c-0359c381c294",
    "vertices" : [ {
      "x" : -20.68629,
      "y" : -32.0,
      "z" : -59.31371
    }, {
      "x" : 43.31371,
      "y" : -32.0,
      "z" : -59.31371
    }, {
      "x" : 43.31371,
      "y" : 32.0,
      "z" : -59.31371
    }, {
      "x" : -20.68629,
      "y" : 32.0,
      "z" : -59.31371
    } ],
    "faces" : [ {
      "vertices" : [ 0, 1, 2 ]
    }, {
      "vertices" : [ 0, 2, 3 ]
    }, {
      "vertices" : [ 0, 3, 2 ]
    }, {
      "vertices" : [ 0, 2, 1 ]
    } ]
  }, {
    "id" : "3db151a4-b46f-4335-bf59-774260edb4e2",
    "vertices" : [ {
      "x" : 27.25,
      "y" : -0.25,
      "z" : 27.75
    }, {
      "x" : 0.75,
      "y" : 0.25,
      "z" : 0.25
    }, {
      "x" : 0.25,
      "y" : 0.25,
      "z" : 0.75
    }, {
      "x" : 27.25,
      "y" : 0.25,
      "z" : 27.75
    }, {
      "x" : 27.75,
      "y" : 0.25,
      "z" : 27.25
    }, {
      "x" : 28.0,
      "y" : 0.0,
      "z" : 28.0
    }, {
      "x" : 0.75,
      "y" : -0.25,
      "z" : 0.25
    }, {
      "x" : 27.75,
      "y" : -0.25,
      "z" : 27.25
    }, {
      "x" : 0.25,
      "y" : -0.25,
      "z" : 0.75
    } ],
    "faces" : [ {
      "vertices" : [ 1, 4, 7 ]
    }, {
      "vertices" : [ 1, 7, 6 ]
    }, {
      "vertices" : [ 0, 8, 6 ]
    }, {
      "vertices" : [ 0, 6, 7 ]
    }, {
      "vertices" : [ 1, 2, 3 ]
    }, {
      "vertices" : [ 1, 3, 4 ]
    }, {
      "vertices" : [ 0, 3, 2 ]
    }, {
      "vertices" : [ 0, 2, 8 ]
    } ]
  } ],
  "instances" : [ {
    "shape" : "fb1507dd-ee38-4bf9-9c09-b1ecd025d785",
    "color" : "#FFFFFF",
    "position" : {
      "x" : 38.62742,
      "y" : 0.0,
      "z" : -59.31371
    }
  }, {
    "shape" : "4c9597d6-30d9-4032-beef-c8b010f6a888",
    "color" : "#00CC00",
    "position" : {
      "x" : 19.31371,
      "y" : -8.0,
      "z" : -8.0
    },
    "orientation" : 19
  }, {
    "shape" : "21f47278-1ceb-4c52-b67f-5b959da5e322",
    "color" : "#00CC00",
    "position" : {
      "x" : -32.0,
      "y" : -13.656855,
      "z" : 5.656854
    },
    "orientation" : 17
  }, {
    "shape" : "87af3d82-ce02-46c4-9e55-c23a4bd5d149",
    "color" : "#FFFF00",
    "position" : {
      "x" : 13.656855,
      "y" : 5.656854,
      "z" : 5.656854
    },
    "orientation" : 0
  }, {
    "shape" : "fb1507dd-ee38-4bf9-9c09-b1ecd025d785",
    "color" : "#FFFFFF",
    "position" : {
      "x" : 11.313708,
      "y" : 51.31371,
      "z" : -27.31371
    }
  }, {
    "shape" : "fb1507dd-ee38-4bf9-9c09-b1ecd025d785",
    "color" : "#FFFFFF",
    "position" : {
      "x" : 19.31371,
      "y" : -19.31371,
      "z" : 0.0
    }
  }, {
    "shape" : "fb1507dd-ee38-4bf9-9c09-b1ecd025d785",
    "color" : "#FFFFFF",
    "position" : {
      "x" : 0.0,
      "y" : 51.31371,
      "z" : 0.0
    }
  }, {
    "shape" : "21f47278-1ceb-4c52-b67f-5b959da5e322",
    "color" : "#3333FF",
    "position" : {
      "x" : -32.0,
      "y" : -13.656855,
      "z" : -13.656855
    },
    "orientation" : 18
  }, {
    "shape" : "7e88e7b3-3737-44bb-8ee6-72e2ff7736b2",
    "color" : "#FFFF00",
    "position" : {
      "x" : 13.656855,
      "y" : 51.31371,
      "z" : 5.656854
    },
    "orientation" : 1
  }, {
    "shape" : "fb1507dd-ee38-4bf9-9c09-b1ecd025d785",
    "color" : "#FFFFFF",
    "position" : {
      "x" : 97.941124,
      "y" : 51.31371,
      "z" : 5.656854
    }
  }, {
    "shape" : "0a7b0236-3b72-4ad6-be57-4a2253ea6315",
    "color" : "#FFFF00",
    "position" : {
      "x" : 70.62742,
      "y" : 51.31371,
      "z" : -21.656855
    },
    "orientation" : 12
  }, {
    "shape" : "99d39fe5-0c6b-44dc-9054-22d0a2f9b241",
    "color" : "#3333FF",
    "position" : {
      "x" : 78.62742,
      "y" : 51.31371,
      "z" : 19.31371
    },
    "orientation" : 0
  }, {
    "shape" : "21f47278-1ceb-4c52-b67f-5b959da5e322",
    "color" : "#FF3333",
    "position" : {
      "x" : 13.656855,
      "y" : 51.31371,
      "z" : 5.656854
    },
    "orientation" : 0
  }, {
    "shape" : "d4858e14-52d5-42eb-a50e-9361c57d7ebd",
    "color" : "#FF3333",
    "position" : {
      "x" : 70.62742,
      "y" : 51.31371,
      "z" : -21.656855
    },
    "orientation" : 2
  }, {
    "shape" : "fb1507dd-ee38-4bf9-9c09-b1ecd025d785",
    "color" : "#FFFFFF",
    "position" : {
      "x" : 19.31371,
      "y" : -8.0,
      "z" : -59.31371
    }
  }, {
    "shape" : "fb1507dd-ee38-4bf9-9c09-b1ecd025d785",
    "color" : "#FFFFFF",
    "position" : {
      "x" : 27.31371,
      "y" : 0.0,
      "z" : -59.31371
    }
  }, {
    "shape" : "7e88e7b3-3737-44bb-8ee6-72e2ff7736b2",
    "color" : "#FF3333",
    "position" : {
      "x" : -32.0,
      "y" : 0.0,
      "z" : -27.31371
    },
    "orientation" : 23
  }, {
    "shape" : "21f47278-1ceb-4c52-b67f-5b959da5e322",
    "color" : "#00CC00",
    "position" : {
      "x" : -32.0,
      "y" : 13.656855,
      "z" : 5.656854
    },
    "orientation" : 19
  }, {
    "shape" : "7e88e7b3-3737-44bb-8ee6-72e2ff7736b2",
    "color" : "#FF3333",
    "position" : {
      "x" : 5.656854,
      "y" : 13.656855,
      "z" : -59.31371
    },
    "orientation" : 12
  }, {
    "shape" : "7e88e7b3-3737-44bb-8ee6-72e2ff7736b2",
    "color" : "#00CC00",
    "position" : {
      "x" : 13.656855,
      "y" : -5.656854,
      "z" : -59.31371
    },
    "orientation" : 5
  }, {
    "shape" : "4c9597d6-30d9-4032-beef-c8b010f6a888",
    "color" : "#00CC00",
    "position" : {
      "x" : 24.970562,
      "y" : -5.656854,
      "z" : -13.656855
    },
    "orientation" : 19
  }, {
    "shape" : "fb1507dd-ee38-4bf9-9c09-b1ecd025d785",
    "color" : "#FFFFFF",
    "position" : {
      "x" : 32.970562,
      "y" : 13.656855,
      "z" : -59.31371
    }
  }, {
    "shape" : "21f47278-1ceb-4c52-b67f-5b959da5e322",
    "color" : "#FF3333",
    "position" : {
      "x" : 19.31371,
      "y" : 51.31371,
      "z" : -8.0
    },
    "orientation" : 0
  }, {
    "shape" : "fb1507dd-ee38-4bf9-9c09-b1ecd025d785",
    "color" : "#FFFFFF",
    "position" : {
      "x" : 70.62742,
      "y" : 51.31371,
      "z" : -13.656855
    }
  }, {
    "shape" : "7e88e7b3-3737-44bb-8ee6-72e2ff7736b2",
    "color" : "#FF3333",
    "position" : {
      "x" : -32.0,
      "y" : 13.656855,
      "z" : -13.656855
    },
    "orientation" : 23
  }, {
    "shape" : "fb1507dd-ee38-4bf9-9c09-b1ecd025d785",
    "color" : "#FFFFFF",
    "position" : {
      "x" : 32.970562,
      "y" : -13.656855,
      "z" : 5.656854
    }
  }, {
    "shape" : "4c9597d6-30d9-4032-beef-c8b010f6a888",
    "color" : "#FF3333",
    "position" : {
      "x" : 5.656854,
      "y" : -13.656855,
      "z" : -13.656855
    },
    "orientation" : 23
  }, {
    "shape" : "02d2ab73-f5b6-4324-9d2d-c9907fb04a62",
    "color" : "#028235",
    "position" : {
      "x" : 19.31371,
      "y" : 19.31371,
      "z" : -8.0
    },
    "orientation" : 1
  }, {
    "shape" : "7e88e7b3-3737-44bb-8ee6-72e2ff7736b2",
    "color" : "#3333FF",
    "position" : {
      "x" : 32.970562,
      "y" : -13.656855,
      "z" : -59.31371
    },
    "orientation" : 7
  }, {
    "shape" : "f8b4c7ca-148d-4a72-9d06-6ad5e5177196",
    "color" : "#FFFF00",
    "position" : {
      "x" : -32.0,
      "y" : 0.0,
      "z" : -8.0
    },
    "orientation" : 19
  }, {
    "shape" : "7e88e7b3-3737-44bb-8ee6-72e2ff7736b2",
    "color" : "#FF3333",
    "position" : {
      "x" : 5.656854,
      "y" : -13.656855,
      "z" : -59.31371
    },
    "orientation" : 12
  }, {
    "shape" : "fb1507dd-ee38-4bf9-9c09-b1ecd025d785",
    "color" : "#FFFFFF",
    "position" : {
      "x" : -32.0,
      "y" : 8.0,
      "z" : 0.0
    }
  }, {
    "shape" : "99d39fe5-0c6b-44dc-9054-22d0a2f9b241",
    "color" : "#3333FF",
    "position" : {
      "x" : 43.31371,
      "y" : 51.31371,
      "z" : -13.656855
    },
    "orientation" : 14
  }, {
    "shape" : "5b4381aa-fcb4-4876-9af1-ead25f48c954",
    "color" : "#FFFFFF",
    "position" : {
      "x" : 0.0,
      "y" : 0.0,
      "z" : 0.0
    }
  }, {
    "shape" : "fb1507dd-ee38-4bf9-9c09-b1ecd025d785",
    "color" : "#FFFFFF",
    "position" : {
      "x" : 70.62742,
      "y" : 51.31371,
      "z" : -21.656855
    }
  }, {
    "shape" : "4c9597d6-30d9-4032-beef-c8b010f6a888",
    "color" : "#3333FF",
    "position" : {
      "x" : 5.656854,
      "y" : -13.656855,
      "z" : -13.656855
    },
    "orientation" : 7
  }, {
    "shape" : "fb1507dd-ee38-4bf9-9c09-b1ecd025d785",
    "color" : "#FFFFFF",
    "position" : {
      "x" : -32.0,
      "y" : 32.0,
      "z" : 32.0
    }
  }, {
    "shape" : "d4858e14-52d5-42eb-a50e-9361c57d7ebd",
    "color" : "#FF3333",
    "position" : {
      "x" : 59.31371,
      "y" : 51.31371,
      "z" : 5.656854
    },
    "orientation" : 2
  }, {
    "shape" : "d4858e14-52d5-42eb-a50e-9361c57d7ebd",
    "color" : "#FF3333",
    "position" : {
      "x" : 78.62742,
      "y" : 51.31371,
      "z" : -8.0
    },
    "orientation" : 2
  }, {
    "shape" : "4c9597d6-30d9-4032-beef-c8b010f6a888",
    "color" : "#FF3333",
    "position" : {
      "x" : 5.656854,
      "y" : 13.656855,
      "z" : -13.656855
    },
    "orientation" : 23
  }, {
    "shape" : "87af3d82-ce02-46c4-9e55-c23a4bd5d149",
    "color" : "#FFFF00",
    "position" : {
      "x" : 19.31371,
      "y" : 8.0,
      "z" : 0.0
    },
    "orientation" : 15
  }, {
    "shape" : "fb1507dd-ee38-4bf9-9c09-b1ecd025d785",
    "color" : "#FFFFFF",
    "position" : {
      "x" : 24.970562,
      "y" : -5.656854,
      "z" : -59.31371
    }
  }, {
    "shape" : "7e88e7b3-3737-44bb-8ee6-72e2ff7736b2",
    "color" : "#FFFF00",
    "position" : {
      "x" : 24.970562,
      "y" : 51.31371,
      "z" : -21.656855
    },
    "orientation" : 1
  }, {
    "shape" : "4c9597d6-30d9-4032-beef-c8b010f6a888",
    "color" : "#3333FF",
    "position" : {
      "x" : 32.970562,
      "y" : -13.656855,
      "z" : 5.656854
    },
    "orientation" : 7
  }, {
    "shape" : "7e88e7b3-3737-44bb-8ee6-72e2ff7736b2",
    "color" : "#FFFF00",
    "position" : {
      "x" : 19.31371,
      "y" : 8.0,
      "z" : -59.31371
    },
    "orientation" : 14
  }, {
    "shape" : "fb1507dd-ee38-4bf9-9c09-b1ecd025d785",
    "color" : "#FFFFFF",
    "position" : {
      "x" : -32.0,
      "y" : 0.0,
      "z" : 0.0
    }
  }, {
    "shape" : "7e88e7b3-3737-44bb-8ee6-72e2ff7736b2",
    "color" : "#FF3333",
    "position" : {
      "x" : -32.0,
      "y" : 5.656854,
      "z" : 5.656854
    },
    "orientation" : 23
  }, {
    "shape" : "7e88e7b3-3737-44bb-8ee6-72e2ff7736b2",
    "color" : "#00CC00",
    "position" : {
      "x" : 19.31371,
      "y" : -8.0,
      "z" : -59.31371
    },
    "orientation" : 19
  }, {
    "shape" : "21f47278-1ceb-4c52-b67f-5b959da5e322",
    "color" : "#00CC00",
    "position" : {
      "x" : -32.0,
      "y" : -13.656855,
      "z" : -13.656855
    },
    "orientation" : 17
  }, {
    "shape" : "21f47278-1ceb-4c52-b67f-5b959da5e322",
    "color" : "#00CC00",
    "position" : {
      "x" : -32.0,
      "y" : -5.656854,
      "z" : 13.656855
    },
    "orientation" : 19
  }, {
    "shape" : "4c9597d6-30d9-4032-beef-c8b010f6a888",
    "color" : "#00CC00",
    "position" : {
      "x" : 32.970562,
      "y" : 13.656855,
      "z" : 5.656854
    },
    "orientation" : 4
  }, {
    "shape" : "4c9597d6-30d9-4032-beef-c8b010f6a888",
    "color" : "#FF3333",
    "position" : {
      "x" : 11.313708,
      "y" : 0.0,
      "z" : -27.31371
    },
    "orientation" : 23
  }, {
    "shape" : "fb1507dd-ee38-4bf9-9c09-b1ecd025d785",
    "color" : "#FFFFFF",
    "position" : {
      "x" : 81.941124,
      "y" : 51.31371,
      "z" : -13.656855
    }
  }, {
    "shape" : "7e88e7b3-3737-44bb-8ee6-72e2ff7736b2",
    "color" : "#00CC00",
    "position" : {
      "x" : 11.313708,
      "y" : 0.0,
      "z" : -59.31371
    },
    "orientation" : 19
  }, {
    "shape" : "fb1507dd-ee38-4bf9-9c09-b1ecd025d785",
    "color" : "#3333FF",
    "position" : {
      "x" : -32.0,
      "y" : 13.656855,
      "z" : -13.656855
    }
  }, {
    "shape" : "fb1507dd-ee38-4bf9-9c09-b1ecd025d785",
    "color" : "#FFFFFF",
    "position" : {
      "x" : -32.0,
      "y" : 0.0,
      "z" : -8.0
    }
  }, {
    "shape" : "fb1507dd-ee38-4bf9-9c09-b1ecd025d785",
    "color" : "#FFFFFF",
    "position" : {
      "x" : 13.656855,
      "y" : -5.656854,
      "z" : 13.656855
    }
  }, {
    "shape" : "7e88e7b3-3737-44bb-8ee6-72e2ff7736b2",
    "color" : "#FFFF00",
    "position" : {
      "x" : 19.31371,
      "y" : -19.31371,
      "z" : -59.31371
    },
    "orientation" : 14
  }, {
    "shape" : "7e88e7b3-3737-44bb-8ee6-72e2ff7736b2",
    "color" : "#00CC00",
    "position" : {
      "x" : 19.31371,
      "y" : 51.31371,
      "z" : 0.0
    },
    "orientation" : 4
  }, {
    "shape" : "21f47278-1ceb-4c52-b67f-5b959da5e322",
    "color" : "#3333FF",
    "position" : {
      "x" : -32.0,
      "y" : -13.656855,
      "z" : 5.656854
    },
    "orientation" : 18
  }, {
    "shape" : "7e88e7b3-3737-44bb-8ee6-72e2ff7736b2",
    "color" : "#3333FF",
    "position" : {
      "x" : 13.656855,
      "y" : 5.656854,
      "z" : -59.31371
    },
    "orientation" : 7
  }, {
    "shape" : "fb1507dd-ee38-4bf9-9c09-b1ecd025d785",
    "color" : "#FFFFFF",
    "position" : {
      "x" : 28.970562,
      "y" : 9.656855,
      "z" : -21.656855
    }
  }, {
    "shape" : "d4858e14-52d5-42eb-a50e-9361c57d7ebd",
    "color" : "#FF3333",
    "position" : {
      "x" : 62.62742,
      "y" : 51.31371,
      "z" : -27.31371
    },
    "orientation" : 2
  }, {
    "shape" : "fb1507dd-ee38-4bf9-9c09-b1ecd025d785",
    "color" : "#FFFFFF",
    "position" : {
      "x" : 19.31371,
      "y" : 8.0,
      "z" : 0.0
    }
  }, {
    "shape" : "fb1507dd-ee38-4bf9-9c09-b1ecd025d785",
    "color" : "#FFFFFF",
    "position" : {
      "x" : 19.31371,
      "y" : -19.31371,
      "z" : -59.31371
    }
  }, {
    "shape" : "0a7b0236-3b72-4ad6-be57-4a2253ea6315",
    "color" : "#FFFF00",
    "position" : {
      "x" : 70.62742,
      "y" : 51.31371,
      "z" : 13.656855
    },
    "orientation" : 2
  }, {
    "shape" : "4c9597d6-30d9-4032-beef-c8b010f6a888",
    "color" : "#FF3333",
    "position" : {
      "x" : 24.970562,
      "y" : 5.656854,
      "z" : -21.656855
    },
    "orientation" : 23
  }, {
    "shape" : "21f47278-1ceb-4c52-b67f-5b959da5e322",
    "color" : "#3333FF",
    "position" : {
      "x" : -32.0,
      "y" : -19.31371,
      "z" : 0.0
    },
    "orientation" : 18
  }, {
    "shape" : "7e88e7b3-3737-44bb-8ee6-72e2ff7736b2",
    "color" : "#FF3333",
    "position" : {
      "x" : -32.0,
      "y" : 5.656854,
      "z" : -21.656855
    },
    "orientation" : 23
  }, {
    "shape" : "fb1507dd-ee38-4bf9-9c09-b1ecd025d785",
    "color" : "#FFFFFF",
    "position" : {
      "x" : 51.31371,
      "y" : 51.31371,
      "z" : -8.0
    }
  }, {
    "shape" : "7e88e7b3-3737-44bb-8ee6-72e2ff7736b2",
    "color" : "#00CC00",
    "position" : {
      "x" : 13.656855,
      "y" : 51.31371,
      "z" : 5.656854
    },
    "orientation" : 4
  }, {
    "shape" : "7e88e7b3-3737-44bb-8ee6-72e2ff7736b2",
    "color" : "#FFFF00",
    "position" : {
      "x" : 13.656855,
      "y" : -5.656854,
      "z" : -59.31371
    },
    "orientation" : 14
  }, {
    "shape" : "fb1507dd-ee38-4bf9-9c09-b1ecd025d785",
    "color" : "#FFFFFF",
    "position" : {
      "x" : 0.0,
      "y" : 0.0,
      "z" : 0.0
    }
  }, {
    "shape" : "fb1507dd-ee38-4bf9-9c09-b1ecd025d785",
    "color" : "#FFFFFF",
    "position" : {
      "x" : -32.0,
      "y" : 32.0,
      "z" : -32.0
    }
  }, {
    "shape" : "fb1507dd-ee38-4bf9-9c09-b1ecd025d785",
    "color" : "#FFFFFF",
    "position" : {
      "x" : 32.970562,
      "y" : 13.656855,
      "z" : 5.656854
    }
  }, {
    "shape" : "7e88e7b3-3737-44bb-8ee6-72e2ff7736b2",
    "color" : "#00CC00",
    "position" : {
      "x" : 19.31371,
      "y" : 19.31371,
      "z" : -59.31371
    },
    "orientation" : 5
  }, {
    "shape" : "4c9597d6-30d9-4032-beef-c8b010f6a888",
    "color" : "#3333FF",
    "position" : {
      "x" : 13.656855,
      "y" : 5.656854,
      "z" : 5.656854
    },
    "orientation" : 7
  }, {
    "shape" : "7e88e7b3-3737-44bb-8ee6-72e2ff7736b2",
    "color" : "#00CC00",
    "position" : {
      "x" : 5.656854,
      "y" : 51.31371,
      "z" : -13.656855
    },
    "orientation" : 18
  }, {
    "shape" : "21f47278-1ceb-4c52-b67f-5b959da5e322",
    "color" : "#00CC00",
    "position" : {
      "x" : -32.0,
      "y" : 0.0,
      "z" : -27.31371
    },
    "orientation" : 17
  }, {
    "shape" : "fb1507dd-ee38-4bf9-9c09-b1ecd025d785",
    "color" : "#FFFFFF",
    "position" : {
      "x" : 19.31371,
      "y" : 19.31371,
      "z" : -8.0
    }
  }, {
    "shape" : "fb1507dd-ee38-4bf9-9c09-b1ecd025d785",
    "color" : "#FFFFFF",
    "position" : {
      "x" : 32.970562,
      "y" : -13.656855,
      "z" : -59.31371
    }
  }, {
    "shape" : "fb1507dd-ee38-4bf9-9c09-b1ecd025d785",
    "color" : "#FFFFFF",
    "position" : {
      "x" : 19.31371,
      "y" : -8.0,
      "z" : -8.0
    }
  }, {
    "shape" : "f8b4c7ca-148d-4a72-9d06-6ad5e5177196",
    "color" : "#FFFF00",
    "position" : {
      "x" : -32.0,
      "y" : 5.656854,
      "z" : -21.656855
    },
    "orientation" : 19
  }, {
    "shape" : "fb1507dd-ee38-4bf9-9c09-b1ecd025d785",
    "color" : "#00CC00",
    "position" : {
      "x" : -32.0,
      "y" : -13.656855,
      "z" : -13.656855
    }
  }, {
    "shape" : "87af3d82-ce02-46c4-9e55-c23a4bd5d149",
    "color" : "#FFFF00",
    "position" : {
      "x" : 38.62742,
      "y" : 0.0,
      "z" : -8.0
    },
    "orientation" : 0
  }, {
    "shape" : "7e88e7b3-3737-44bb-8ee6-72e2ff7736b2",
    "color" : "#FF3333",
    "position" : {
      "x" : 13.656855,
      "y" : 5.656854,
      "z" : -59.31371
    },
    "orientation" : 12
  }, {
    "shape" : "d4858e14-52d5-42eb-a50e-9361c57d7ebd",
    "color" : "#00CC00",
    "position" : {
      "x" : 70.62742,
      "y" : 51.31371,
      "z" : 13.656855
    },
    "orientation" : 0
  }, {
    "shape" : "fb1507dd-ee38-4bf9-9c09-b1ecd025d785",
    "color" : "#FFFFFF",
    "position" : {
      "x" : 13.656855,
      "y" : 5.656854,
      "z" : 5.656854
    }
  }, {
    "shape" : "fb1507dd-ee38-4bf9-9c09-b1ecd025d785",
    "color" : "#FFFFFF",
    "position" : {
      "x" : 43.31371,
      "y" : -32.0,
      "z" : -59.31371
    }
  }, {
    "shape" : "fb1507dd-ee38-4bf9-9c09-b1ecd025d785",
    "color" : "#FFFFFF",
    "position" : {
      "x" : -32.0,
      "y" : 19.31371,
      "z" : -8.0
    }
  }, {
    "shape" : "fb1507dd-ee38-4bf9-9c09-b1ecd025d785",
    "color" : "#FFFFFF",
    "position" : {
      "x" : -32.0,
      "y" : 13.656855,
      "z" : 5.656854
    }
  }, {
    "shape" : "fb1507dd-ee38-4bf9-9c09-b1ecd025d785",
    "color" : "#FFFFFF",
    "position" : {
      "x" : 27.31371,
      "y" : 0.0,
      "z" : 19.31371
    }
  }, {
    "shape" : "4c9597d6-30d9-4032-beef-c8b010f6a888",
    "color" : "#00CC00",
    "position" : {
      "x" : 32.970562,
      "y" : -13.656855,
      "z" : 5.656854
    },
    "orientation" : 19
  }, {
    "shape" : "fb1507dd-ee38-4bf9-9c09-b1ecd025d785",
    "color" : "#FFFFFF",
    "position" : {
      "x" : -32.0,
      "y" : 5.656854,
      "z" : -21.656855
    }
  }, {
    "shape" : "0a7b0236-3b72-4ad6-be57-4a2253ea6315",
    "color" : "#FFFF00",
    "position" : {
      "x" : 70.62742,
      "y" : 51.31371,
      "z" : -13.656855
    },
    "orientation" : 2
  }, {
    "shape" : "fb1507dd-ee38-4bf9-9c09-b1ecd025d785",
    "color" : "#FFFFFF",
    "position" : {
      "x" : -32.0,
      "y" : -5.656854,
      "z" : -13.656855
    }
  }, {
    "shape" : "87af3d82-ce02-46c4-9e55-c23a4bd5d149",
    "color" : "#FFFF00",
    "position" : {
      "x" : 13.656855,
      "y" : -5.656854,
      "z" : 13.656855
    },
    "orientation" : 15
  }, {
    "shape" : "fb1507dd-ee38-4bf9-9c09-b1ecd025d785",
    "color" : "#FFFFFF",
    "position" : {
      "x" : 62.62742,
      "y" : 51.31371,
      "z" : 0.0
    }
  }, {
    "shape" : "fb1507dd-ee38-4bf9-9c09-b1ecd025d785",
    "color" : "#FFFFFF",
    "position" : {
      "x" : 19.31371,
      "y" : 51.31371,
      "z" : 0.0
    }
  }, {
    "shape" : "87af3d82-ce02-46c4-9e55-c23a4bd5d149",
    "color" : "#FFFF00",
    "position" : {
      "x" : 5.656854,
      "y" : -13.656855,
      "z" : -13.656855
    },
    "orientation" : 15
  }, {
    "shape" : "7e88e7b3-3737-44bb-8ee6-72e2ff7736b2",
    "color" : "#FF3333",
    "position" : {
      "x" : 19.31371,
      "y" : -8.0,
      "z" : -59.31371
    },
    "orientation" : 12
  }, {
    "shape" : "7e88e7b3-3737-44bb-8ee6-72e2ff7736b2",
    "color" : "#FFFF00",
    "position" : {
      "x" : 5.656854,
      "y" : 51.31371,
      "z" : -13.656855
    },
    "orientation" : 13
  }, {
    "shape" : "0a7b0236-3b72-4ad6-be57-4a2253ea6315",
    "color" : "#FFFF00",
    "position" : {
      "x" : 62.62742,
      "y" : 51.31371,
      "z" : 0.0
    },
    "orientation" : 2
  }, {
    "shape" : "0a7b0236-3b72-4ad6-be57-4a2253ea6315",
    "color" : "#FFFF00",
    "position" : {
      "x" : 43.31371,
      "y" : 51.31371,
      "z" : -13.656855
    },
    "orientation" : 2
  }, {
    "shape" : "f8b4c7ca-148d-4a72-9d06-6ad5e5177196",
    "color" : "#FFFF00",
    "position" : {
      "x" : -32.0,
      "y" : 5.656854,
      "z" : 5.656854
    },
    "orientation" : 19
  }, {
    "shape" : "7e88e7b3-3737-44bb-8ee6-72e2ff7736b2",
    "color" : "#FFFF00",
    "position" : {
      "x" : 19.31371,
      "y" : 51.31371,
      "z" : 0.0
    },
    "orientation" : 13
  }, {
    "shape" : "7e88e7b3-3737-44bb-8ee6-72e2ff7736b2",
    "color" : "#00CC00",
    "position" : {
      "x" : 19.31371,
      "y" : 51.31371,
      "z" : -8.0
    },
    "orientation" : 4
  }, {
    "shape" : "4c9597d6-30d9-4032-beef-c8b010f6a888",
    "color" : "#00CC00",
    "position" : {
      "x" : 5.656854,
      "y" : -13.656855,
      "z" : -13.656855
    },
    "orientation" : 19
  }, {
    "shape" : "7e88e7b3-3737-44bb-8ee6-72e2ff7736b2",
    "color" : "#3333FF",
    "position" : {
      "x" : 13.656855,
      "y" : -5.656854,
      "z" : -59.31371
    },
    "orientation" : 7
  }, {
    "shape" : "fb1507dd-ee38-4bf9-9c09-b1ecd025d785",
    "color" : "#FFFFFF",
    "position" : {
      "x" : -20.68629,
      "y" : -32.0,
      "z" : -59.31371
    }
  }, {
    "shape" : "7e88e7b3-3737-44bb-8ee6-72e2ff7736b2",
    "color" : "#3333FF",
    "position" : {
      "x" : 19.31371,
      "y" : -19.31371,
      "z" : -59.31371
    },
    "orientation" : 7
  }, {
    "shape" : "7e88e7b3-3737-44bb-8ee6-72e2ff7736b2",
    "color" : "#00CC00",
    "position" : {
      "x" : 24.970562,
      "y" : -5.656854,
      "z" : -59.31371
    },
    "orientation" : 19
  }, {
    "shape" : "99d39fe5-0c6b-44dc-9054-22d0a2f9b241",
    "color" : "#3333FF",
    "position" : {
      "x" : 78.62742,
      "y" : 51.31371,
      "z" : -8.0
    },
    "orientation" : 0
  }, {
    "shape" : "4c9597d6-30d9-4032-beef-c8b010f6a888",
    "color" : "#FF3333",
    "position" : {
      "x" : 13.656855,
      "y" : -5.656854,
      "z" : 13.656855
    },
    "orientation" : 0
  }, {
    "shape" : "0a7b0236-3b72-4ad6-be57-4a2253ea6315",
    "color" : "#FFFF00",
    "position" : {
      "x" : 89.941124,
      "y" : 51.31371,
      "z" : 0.0
    },
    "orientation" : 2
  }, {
    "shape" : "fb1507dd-ee38-4bf9-9c09-b1ecd025d785",
    "color" : "#FFFFFF",
    "position" : {
      "x" : 24.970562,
      "y" : 51.31371,
      "z" : -13.656855
    }
  }, {
    "shape" : "36332ae0-e70e-4216-b55f-7cc0c49bb5dd",
    "color" : "#028235",
    "position" : {
      "x" : 70.62742,
      "y" : 51.31371,
      "z" : -21.656855
    },
    "orientation" : 15
  }, {
    "shape" : "7e88e7b3-3737-44bb-8ee6-72e2ff7736b2",
    "color" : "#3333FF",
    "position" : {
      "x" : 5.656854,
      "y" : -13.656855,
      "z" : -59.31371
    },
    "orientation" : 7
  }, {
    "shape" : "21f47278-1ceb-4c52-b67f-5b959da5e322",
    "color" : "#00CC00",
    "position" : {
      "x" : -32.0,
      "y" : -5.656854,
      "z" : -13.656855
    },
    "orientation" : 17
  }, {
    "shape" : "d4858e14-52d5-42eb-a50e-9361c57d7ebd",
    "color" : "#00CC00",
    "position" : {
      "x" : 62.62742,
      "y" : 51.31371,
      "z" : -27.31371
    },
    "orientation" : 14
  }, {
    "shape" : "fb1507dd-ee38-4bf9-9c09-b1ecd025d785",
    "color" : "#3333FF",
    "position" : {
      "x" : 5.656854,
      "y" : 51.31371,
      "z" : -13.656855
    }
  }, {
    "shape" : "fb1507dd-ee38-4bf9-9c09-b1ecd025d785",
    "color" : "#FFFFFF",
    "position" : {
      "x" : 51.31371,
      "y" : 51.31371,
      "z" : -40.0
    }
  }, {
    "shape" : "7e88e7b3-3737-44bb-8ee6-72e2ff7736b2",
    "color" : "#3333FF",
    "position" : {
      "x" : 32.970562,
      "y" : 51.31371,
      "z" : 5.656854
    },
    "orientation" : 4
  }, {
    "shape" : "fb1507dd-ee38-4bf9-9c09-b1ecd025d785",
    "color" : "#FFFFFF",
    "position" : {
      "x" : 43.31371,
      "y" : 51.31371,
      "z" : -13.656855
    }
  }, {
    "shape" : "d4858e14-52d5-42eb-a50e-9361c57d7ebd",
    "color" : "#00CC00",
    "position" : {
      "x" : 70.62742,
      "y" : 51.31371,
      "z" : -13.656855
    },
    "orientation" : 14
  }, {
    "shape" : "7e88e7b3-3737-44bb-8ee6-72e2ff7736b2",
    "color" : "#3333FF",
    "position" : {
      "x" : 19.31371,
      "y" : -8.0,
      "z" : -59.31371
    },
    "orientation" : 7
  }, {
    "shape" : "fb1507dd-ee38-4bf9-9c09-b1ecd025d785",
    "color" : "#FFFFFF",
    "position" : {
      "x" : 11.313708,
      "y" : 0.0,
      "z" : -27.31371
    }
  }, {
    "shape" : "0a7b0236-3b72-4ad6-be57-4a2253ea6315",
    "color" : "#FFFF00",
    "position" : {
      "x" : 59.31371,
      "y" : 51.31371,
      "z" : 5.656854
    },
    "orientation" : 12
  }, {
    "shape" : "4c9597d6-30d9-4032-beef-c8b010f6a888",
    "color" : "#3333FF",
    "position" : {
      "x" : 13.656855,
      "y" : -5.656854,
      "z" : 13.656855
    },
    "orientation" : 7
  }, {
    "shape" : "fb1507dd-ee38-4bf9-9c09-b1ecd025d785",
    "color" : "#FFFFFF",
    "position" : {
      "x" : 38.62742,
      "y" : 0.0,
      "z" : -8.0
    }
  }, {
    "shape" : "fb1507dd-ee38-4bf9-9c09-b1ecd025d785",
    "color" : "#FFFFFF",
    "position" : {
      "x" : 23.31371,
      "y" : 23.31371,
      "z" : -8.0
    }
  }, {
    "shape" : "fb1507dd-ee38-4bf9-9c09-b1ecd025d785",
    "color" : "#FFFFFF",
    "position" : {
      "x" : 78.62742,
      "y" : 51.31371,
      "z" : -8.0
    }
  }, {
    "shape" : "d4858e14-52d5-42eb-a50e-9361c57d7ebd",
    "color" : "#00CC00",
    "position" : {
      "x" : 81.941124,
      "y" : 51.31371,
      "z" : -13.656855
    },
    "orientation" : 14
  }, {
    "shape" : "463a63cf-d01b-440e-8047-c3b6ca4c797f",
    "color" : "#FFFFFF",
    "position" : {
      "x" : 0.0,
      "y" : 0.0,
      "z" : 0.0
    }
  }, {
    "shape" : "7e88e7b3-3737-44bb-8ee6-72e2ff7736b2",
    "color" : "#FFFF00",
    "position" : {
      "x" : 5.656854,
      "y" : -13.656855,
      "z" : -59.31371
    },
    "orientation" : 14
  }, {
    "shape" : "fb1507dd-ee38-4bf9-9c09-b1ecd025d785",
    "color" : "#FFFF00",
    "position" : {
      "x" : -32.0,
      "y" : 5.656854,
      "z" : 5.656854
    }
  }, {
    "shape" : "7e88e7b3-3737-44bb-8ee6-72e2ff7736b2",
    "color" : "#FF3333",
    "position" : {
      "x" : -32.0,
      "y" : -8.0,
      "z" : -8.0
    },
    "orientation" : 23
  }, {
    "shape" : "fb1507dd-ee38-4bf9-9c09-b1ecd025d785",
    "color" : "#FFFFFF",
    "position" : {
      "x" : 5.656854,
      "y" : -13.656855,
      "z" : -13.656855
    }
  }, {
    "shape" : "fb1507dd-ee38-4bf9-9c09-b1ecd025d785",
    "color" : "#FFFFFF",
    "position" : {
      "x" : -12.686292,
      "y" : 51.31371,
      "z" : -40.0
    }
  }, {
    "shape" : "959261da-01ae-4197-8924-efd62286e939",
    "color" : "#FFFFFF",
    "position" : {
      "x" : 0.0,
      "y" : 0.0,
      "z" : 0.0
    }
  }, {
    "shape" : "fb1507dd-ee38-4bf9-9c09-b1ecd025d785",
    "color" : "#FFFFFF",
    "position" : {
      "x" : -32.0,
      "y" : 0.0,
      "z" : 19.31371
    }
  }, {
    "shape" : "fb1507dd-ee38-4bf9-9c09-b1ecd025d785",
    "color" : "#FFFFFF",
    "position" : {
      "x" : -32.0,
      "y" : 0.0,
      "z" : -27.31371
    }
  }, {
    "shape" : "d4858e14-52d5-42eb-a50e-9361c57d7ebd",
    "color" : "#FF3333",
    "position" : {
      "x" : 70.62742,
      "y" : 51.31371,
      "z" : -13.656855
    },
    "orientation" : 2
  }, {
    "shape" : "fb1507dd-ee38-4bf9-9c09-b1ecd025d785",
    "color" : "#FFFFFF",
    "position" : {
      "x" : 59.31371,
      "y" : 51.31371,
      "z" : 5.656854
    }
  }, {
    "shape" : "fb1507dd-ee38-4bf9-9c09-b1ecd025d785",
    "color" : "#FFFFFF",
    "position" : {
      "x" : 51.31371,
      "y" : 51.31371,
      "z" : 24.0
    }
  }, {
    "shape" : "d4858e14-52d5-42eb-a50e-9361c57d7ebd",
    "color" : "#FF3333",
    "position" : {
      "x" : 70.62742,
      "y" : 51.31371,
      "z" : 13.656855
    },
    "orientation" : 12
  }, {
    "shape" : "fb1507dd-ee38-4bf9-9c09-b1ecd025d785",
    "color" : "#FFFFFF",
    "position" : {
      "x" : 19.31371,
      "y" : 51.31371,
      "z" : -8.0
    }
  }, {
    "shape" : "21f47278-1ceb-4c52-b67f-5b959da5e322",
    "color" : "#FF3333",
    "position" : {
      "x" : 13.656855,
      "y" : 51.31371,
      "z" : 13.656855
    },
    "orientation" : 14
  }, {
    "shape" : "7e88e7b3-3737-44bb-8ee6-72e2ff7736b2",
    "color" : "#FFFF00",
    "position" : {
      "x" : 5.656854,
      "y" : 13.656855,
      "z" : -59.31371
    },
    "orientation" : 14
  }, {
    "shape" : "fb1507dd-ee38-4bf9-9c09-b1ecd025d785",
    "color" : "#FFFFFF",
    "position" : {
      "x" : 5.656854,
      "y" : 13.656855,
      "z" : -13.656855
    }
  }, {
    "shape" : "4c9597d6-30d9-4032-beef-c8b010f6a888",
    "color" : "#00CC00",
    "position" : {
      "x" : 11.313708,
      "y" : 0.0,
      "z" : -27.31371
    },
    "orientation" : 19
  }, {
    "shape" : "21f47278-1ceb-4c52-b67f-5b959da5e322",
    "color" : "#00CC00",
    "position" : {
      "x" : -32.0,
      "y" : -8.0,
      "z" : -8.0
    },
    "orientation" : 17
  }, {
    "shape" : "fb1507dd-ee38-4bf9-9c09-b1ecd025d785",
    "color" : "#FFFFFF",
    "position" : {
      "x" : -32.0,
      "y" : -19.31371,
      "z" : 0.0
    }
  }, {
    "shape" : "d4858e14-52d5-42eb-a50e-9361c57d7ebd",
    "color" : "#00CC00",
    "position" : {
      "x" : 97.941124,
      "y" : 51.31371,
      "z" : 5.656854
    },
    "orientation" : 14
  }, {
    "shape" : "fb1507dd-ee38-4bf9-9c09-b1ecd025d785",
    "color" : "#00CC00",
    "position" : {
      "x" : 5.656854,
      "y" : -13.656855,
      "z" : -59.31371
    }
  }, {
    "shape" : "f8b4c7ca-148d-4a72-9d06-6ad5e5177196",
    "color" : "#FFFF00",
    "position" : {
      "x" : -32.0,
      "y" : 8.0,
      "z" : 0.0
    },
    "orientation" : 17
  }, {
    "shape" : "fb1507dd-ee38-4bf9-9c09-b1ecd025d785",
    "color" : "#FFFFFF",
    "position" : {
      "x" : -12.686292,
      "y" : 51.31371,
      "z" : 24.0
    }
  }, {
    "shape" : "7e88e7b3-3737-44bb-8ee6-72e2ff7736b2",
    "color" : "#FF3333",
    "position" : {
      "x" : 13.656855,
      "y" : -5.656854,
      "z" : -59.31371
    },
    "orientation" : 0
  }, {
    "shape" : "ff7d2686-8608-4e47-890c-0359c381c294",
    "color" : "#FFFFFF",
    "position" : {
      "x" : 0.0,
      "y" : 0.0,
      "z" : 0.0
    }
  }, {
    "shape" : "7e88e7b3-3737-44bb-8ee6-72e2ff7736b2",
    "color" : "#00CC00",
    "position" : {
      "x" : 13.656855,
      "y" : 51.31371,
      "z" : 13.656855
    },
    "orientation" : 4
  }, {
    "shape" : "fb1507dd-ee38-4bf9-9c09-b1ecd025d785",
    "color" : "#FFFFFF",
    "position" : {
      "x" : 70.62742,
      "y" : 51.31371,
      "z" : 5.656854
    }
  }, {
    "shape" : "fb1507dd-ee38-4bf9-9c09-b1ecd025d785",
    "color" : "#FFFFFF",
    "position" : {
      "x" : 27.31371,
      "y" : 51.31371,
      "z" : 19.31371
    }
  }, {
    "shape" : "fb1507dd-ee38-4bf9-9c09-b1ecd025d785",
    "color" : "#FFFFFF",
    "position" : {
      "x" : -32.0,
      "y" : -13.656855,
      "z" : 5.656854
    }
  }, {
    "shape" : "87af3d82-ce02-46c4-9e55-c23a4bd5d149",
    "color" : "#FFFF00",
    "position" : {
      "x" : 24.970562,
      "y" : 5.656854,
      "z" : -21.656855
    },
    "orientation" : 0
  }, {
    "shape" : "7e88e7b3-3737-44bb-8ee6-72e2ff7736b2",
    "color" : "#00CC00",
    "position" : {
      "x" : 32.970562,
      "y" : 13.656855,
      "z" : -59.31371
    },
    "orientation" : 5
  }, {
    "shape" : "02d2ab73-f5b6-4324-9d2d-c9907fb04a62",
    "color" : "#028235",
    "position" : {
      "x" : 24.970562,
      "y" : 5.656854,
      "z" : -21.656855
    },
    "orientation" : 1
  }, {
    "shape" : "4c9597d6-30d9-4032-beef-c8b010f6a888",
    "color" : "#3333FF",
    "position" : {
      "x" : 5.656854,
      "y" : 13.656855,
      "z" : -13.656855
    },
    "orientation" : 18
  }, {
    "shape" : "7e88e7b3-3737-44bb-8ee6-72e2ff7736b2",
    "color" : "#FF3333",
    "position" : {
      "x" : 24.970562,
      "y" : 5.656854,
      "z" : -59.31371
    },
    "orientation" : 12
  }, {
    "shape" : "4c9597d6-30d9-4032-beef-c8b010f6a888",
    "color" : "#FF3333",
    "position" : {
      "x" : 19.31371,
      "y" : 19.31371,
      "z" : -8.0
    },
    "orientation" : 23
  }, {
    "shape" : "fb1507dd-ee38-4bf9-9c09-b1ecd025d785",
    "color" : "#FFFFFF",
    "position" : {
      "x" : 89.941124,
      "y" : 51.31371,
      "z" : -8.0
    }
  }, {
    "shape" : "fb1507dd-ee38-4bf9-9c09-b1ecd025d785",
    "color" : "#FFFFFF",
    "position" : {
      "x" : -32.0,
      "y" : -8.0,
      "z" : -8.0
    }
  }, {
    "shape" : "4c9597d6-30d9-4032-beef-c8b010f6a888",
    "color" : "#3333FF",
    "position" : {
      "x" : 19.31371,
      "y" : -8.0,
      "z" : -8.0
    },
    "orientation" : 7
  }, {
    "shape" : "21f47278-1ceb-4c52-b67f-5b959da5e322",
    "color" : "#3333FF",
    "position" : {
      "x" : -32.0,
      "y" : 5.656854,
      "z" : 5.656854
    },
    "orientation" : 18
  }, {
    "shape" : "7e88e7b3-3737-44bb-8ee6-72e2ff7736b2",
    "color" : "#00CC00",
    "position" : {
      "x" : 27.31371,
      "y" : 51.31371,
      "z" : 19.31371
    },
    "orientation" : 4
  }, {
    "shape" : "fb1507dd-ee38-4bf9-9c09-b1ecd025d785",
    "color" : "#FFFFFF",
    "position" : {
      "x" : 24.970562,
      "y" : 5.656854,
      "z" : -59.31371
    }
  }, {
    "shape" : "d4858e14-52d5-42eb-a50e-9361c57d7ebd",
    "color" : "#FF3333",
    "position" : {
      "x" : 43.31371,
      "y" : 51.31371,
      "z" : -13.656855
    },
    "orientation" : 2
  }, {
    "shape" : "7e88e7b3-3737-44bb-8ee6-72e2ff7736b2",
    "color" : "#FF3333",
    "position" : {
      "x" : -32.0,
      "y" : -5.656854,
      "z" : 13.656855
    },
    "orientation" : 21
  }, {
    "shape" : "fb1507dd-ee38-4bf9-9c09-b1ecd025d785",
    "color" : "#3333FF",
    "position" : {
      "x" : 5.656854,
      "y" : 13.656855,
      "z" : -59.31371
    }
  }, {
    "shape" : "fb1507dd-ee38-4bf9-9c09-b1ecd025d785",
    "color" : "#FF3333",
    "position" : {
      "x" : 13.656855,
      "y" : 51.31371,
      "z" : 13.656855
    }
  }, {
    "shape" : "4c9597d6-30d9-4032-beef-c8b010f6a888",
    "color" : "#00CC00",
    "position" : {
      "x" : 13.656855,
      "y" : -5.656854,
      "z" : 13.656855
    },
    "orientation" : 4
  }, {
    "shape" : "87af3d82-ce02-46c4-9e55-c23a4bd5d149",
    "color" : "#FFFF00",
    "position" : {
      "x" : 19.31371,
      "y" : -19.31371,
      "z" : 0.0
    },
    "orientation" : 15
  }, {
    "shape" : "fb1507dd-ee38-4bf9-9c09-b1ecd025d785",
    "color" : "#FFFFFF",
    "position" : {
      "x" : 19.31371,
      "y" : 8.0,
      "z" : -59.31371
    }
  }, {
    "shape" : "fb1507dd-ee38-4bf9-9c09-b1ecd025d785",
    "color" : "#FFFFFF",
    "position" : {
      "x" : 11.313708,
      "y" : 0.0,
      "z" : -59.31371
    }
  }, {
    "shape" : "fb1507dd-ee38-4bf9-9c09-b1ecd025d785",
    "color" : "#FFFFFF",
    "position" : {
      "x" : 24.970562,
      "y" : 5.656854,
      "z" : -21.656855
    }
  }, {
    "shape" : "7e88e7b3-3737-44bb-8ee6-72e2ff7736b2",
    "color" : "#FF3333",
    "position" : {
      "x" : 19.31371,
      "y" : 19.31371,
      "z" : -59.31371
    },
    "orientation" : 12
  }, {
    "shape" : "fb1507dd-ee38-4bf9-9c09-b1ecd025d785",
    "color" : "#FFFFFF",
    "position" : {
      "x" : 62.62742,
      "y" : 51.31371,
      "z" : -27.31371
    }
  }, {
    "shape" : "3db151a4-b46f-4335-bf59-774260edb4e2",
    "color" : "#028235",
    "position" : {
      "x" : 51.31371,
      "y" : 51.31371,
      "z" : -8.0
    },
    "orientation" : 15
  }, {
    "shape" : "fb1507dd-ee38-4bf9-9c09-b1ecd025d785",
    "color" : "#FF3333",
    "position" : {
      "x" : 13.656855,
      "y" : -5.656854,
      "z" : -59.31371
    }
  }, {
    "shape" : "21f47278-1ceb-4c52-b67f-5b959da5e322",
    "color" : "#3333FF",
    "position" : {
      "x" : -32.0,
      "y" : -5.656854,
      "z" : 13.656855
    },
    "orientation" : 18
  }, {
    "shape" : "99d39fe5-0c6b-44dc-9054-22d0a2f9b241",
    "color" : "#3333FF",
    "position" : {
      "x" : 59.31371,
      "y" : 51.31371,
      "z" : 5.656854
    },
    "orientation" : 0
  }, {
    "shape" : "fb1507dd-ee38-4bf9-9c09-b1ecd025d785",
    "color" : "#FFFF00",
    "position" : {
      "x" : 13.656855,
      "y" : 51.31371,
      "z" : 5.656854
    }
  }, {
    "shape" : "fb1507dd-ee38-4bf9-9c09-b1ecd025d785",
    "color" : "#FFFFFF",
    "position" : {
      "x" : 70.62742,
      "y" : 51.31371,
      "z" : 13.656855
    }
  }, {
    "shape" : "99d39fe5-0c6b-44dc-9054-22d0a2f9b241",
    "color" : "#3333FF",
    "position" : {
      "x" : 70.62742,
      "y" : 51.31371,
      "z" : -13.656855
    },
    "orientation" : 0
  }, {
    "shape" : "7e88e7b3-3737-44bb-8ee6-72e2ff7736b2",
    "color" : "#FFFF00",
    "position" : {
      "x" : 24.970562,
      "y" : 5.656854,
      "z" : -59.31371
    },
    "orientation" : 2
  }, {
    "shape" : "fb1507dd-ee38-4bf9-9c09-b1ecd025d785",
    "color" : "#FFFFFF",
    "position" : {
      "x" : 32.970562,
      "y" : 51.31371,
      "z" : 5.656854
    }
  }, {
    "shape" : "fb1507dd-ee38-4bf9-9c09-b1ecd025d785",
    "color" : "#FFFFFF",
    "position" : {
      "x" : 38.62742,
      "y" : 51.31371,
      "z" : -8.0
    }
  }, {
    "shape" : "fb1507dd-ee38-4bf9-9c09-b1ecd025d785",
    "color" : "#FFFFFF",
    "position" : {
      "x" : 78.62742,
      "y" : 51.31371,
      "z" : 19.31371
    }
  }, {
    "shape" : "fb1507dd-ee38-4bf9-9c09-b1ecd025d785",
    "color" : "#FFFFFF",
    "position" : {
      "x" : 24.970562,
      "y" : -5.656854,
      "z" : -13.656855
    }
  }, {
    "shape" : "4c9597d6-30d9-4032-beef-c8b010f6a888",
    "color" : "#00CC00",
    "position" : {
      "x" : 19.31371,
      "y" : 19.31371,
      "z" : -8.0
    },
    "orientation" : 4
  }, {
    "shape" : "21f47278-1ceb-4c52-b67f-5b959da5e322",
    "color" : "#FF3333",
    "position" : {
      "x" : 5.656854,
      "y" : 51.31371,
      "z" : -13.656855
    },
    "orientation" : 0
  }, {
    "shape" : "99d39fe5-0c6b-44dc-9054-22d0a2f9b241",
    "color" : "#3333FF",
    "position" : {
      "x" : 89.941124,
      "y" : 51.31371,
      "z" : 0.0
    },
    "orientation" : 0
  }, {
    "shape" : "7e88e7b3-3737-44bb-8ee6-72e2ff7736b2",
    "color" : "#00CC00",
    "position" : {
      "x" : 32.970562,
      "y" : -13.656855,
      "z" : -59.31371
    },
    "orientation" : 19
  }, {
    "shape" : "21f47278-1ceb-4c52-b67f-5b959da5e322",
    "color" : "#3333FF",
    "position" : {
      "x" : -32.0,
      "y" : 13.656855,
      "z" : -13.656855
    },
    "orientation" : 16
  }, {
    "shape" : "0a7b0236-3b72-4ad6-be57-4a2253ea6315",
    "color" : "#FFFF00",
    "position" : {
      "x" : 89.941124,
      "y" : 51.31371,
      "z" : -8.0
    },
    "orientation" : 12
  }, {
    "shape" : "7e88e7b3-3737-44bb-8ee6-72e2ff7736b2",
    "color" : "#FFFF00",
    "position" : {
      "x" : 38.62742,
      "y" : 51.31371,
      "z" : -8.0
    },
    "orientation" : 1
  }, {
    "shape" : "fb1507dd-ee38-4bf9-9c09-b1ecd025d785",
    "color" : "#FF3333",
    "position" : {
      "x" : -32.0,
      "y" : -5.656854,
      "z" : 13.656855
    }
  }, {
    "shape" : "fb1507dd-ee38-4bf9-9c09-b1ecd025d785",
    "color" : "#FFFFFF",
    "position" : {
      "x" : 43.31371,
      "y" : 32.0,
      "z" : -59.31371
    }
  }, {
    "shape" : "7e88e7b3-3737-44bb-8ee6-72e2ff7736b2",
    "color" : "#FFFF00",
    "position" : {
      "x" : 13.656855,
      "y" : 5.656854,
      "z" : -59.31371
    },
    "orientation" : 2
  }, {
    "shape" : "fb1507dd-ee38-4bf9-9c09-b1ecd025d785",
    "color" : "#FFFF00",
    "position" : {
      "x" : 13.656855,
      "y" : 5.656854,
      "z" : -59.31371
    }
  }, {
    "shape" : "f8b4c7ca-148d-4a72-9d06-6ad5e5177196",
    "color" : "#FFFF00",
    "position" : {
      "x" : -32.0,
      "y" : -5.656854,
      "z" : 13.656855
    },
    "orientation" : 17
  }, {
    "shape" : "7e88e7b3-3737-44bb-8ee6-72e2ff7736b2",
    "color" : "#FFFF00",
    "position" : {
      "x" : 13.656855,
      "y" : 51.31371,
      "z" : 13.656855
    },
    "orientation" : 13
  }, {
    "shape" : "99d39fe5-0c6b-44dc-9054-22d0a2f9b241",
    "color" : "#3333FF",
    "position" : {
      "x" : 97.941124,
      "y" : 51.31371,
      "z" : 5.656854
    },
    "orientation" : 0
  }, {
    "shape" : "7e88e7b3-3737-44bb-8ee6-72e2ff7736b2",
    "color" : "#FF3333",
    "position" : {
      "x" : 11.313708,
      "y" : 0.0,
      "z" : -59.31371
    },
    "orientation" : 12
  }, {
    "shape" : "21f47278-1ceb-4c52-b67f-5b959da5e322",
    "color" : "#FF3333",
    "position" : {
      "x" : 11.313708,
      "y" : 51.31371,
      "z" : -27.31371
    },
    "orientation" : 0
  }, {
    "shape" : "fb1507dd-ee38-4bf9-9c09-b1ecd025d785",
    "color" : "#FFFFFF",
    "position" : {
      "x" : -20.68629,
      "y" : 32.0,
      "z" : -59.31371
    }
  }, {
    "shape" : "f8b4c7ca-148d-4a72-9d06-6ad5e5177196",
    "color" : "#FFFF00",
    "position" : {
      "x" : -32.0,
      "y" : -19.31371,
      "z" : 0.0
    },
    "orientation" : 17
  }, {
    "shape" : "99d39fe5-0c6b-44dc-9054-22d0a2f9b241",
    "color" : "#3333FF",
    "position" : {
      "x" : 70.62742,
      "y" : 51.31371,
      "z" : 13.656855
    },
    "orientation" : 0
  }, {
    "shape" : "4c9597d6-30d9-4032-beef-c8b010f6a888",
    "color" : "#3333FF",
    "position" : {
      "x" : 27.31371,
      "y" : 0.0,
      "z" : 19.31371
    },
    "orientation" : 7
  }, {
    "shape" : "7e88e7b3-3737-44bb-8ee6-72e2ff7736b2",
    "color" : "#3333FF",
    "position" : {
      "x" : 5.656854,
      "y" : 13.656855,
      "z" : -59.31371
    },
    "orientation" : 17
  }, {
    "shape" : "21f47278-1ceb-4c52-b67f-5b959da5e322",
    "color" : "#3333FF",
    "position" : {
      "x" : -32.0,
      "y" : -8.0,
      "z" : -8.0
    },
    "orientation" : 18
  }, {
    "shape" : "d4858e14-52d5-42eb-a50e-9361c57d7ebd",
    "color" : "#00CC00",
    "position" : {
      "x" : 78.62742,
      "y" : 51.31371,
      "z" : -8.0
    },
    "orientation" : 14
  }, {
    "shape" : "fb1507dd-ee38-4bf9-9c09-b1ecd025d785",
    "color" : "#FFFFFF",
    "position" : {
      "x" : 24.970562,
      "y" : 51.31371,
      "z" : -21.656855
    }
  }, {
    "shape" : "4c9597d6-30d9-4032-beef-c8b010f6a888",
    "color" : "#FF3333",
    "position" : {
      "x" : 19.31371,
      "y" : -8.0,
      "z" : -8.0
    },
    "orientation" : 23
  }, {
    "shape" : "21f47278-1ceb-4c52-b67f-5b959da5e322",
    "color" : "#00CC00",
    "position" : {
      "x" : -32.0,
      "y" : 19.31371,
      "z" : -8.0
    },
    "orientation" : 19
  }, {
    "shape" : "87af3d82-ce02-46c4-9e55-c23a4bd5d149",
    "color" : "#FFFF00",
    "position" : {
      "x" : 5.656854,
      "y" : 13.656855,
      "z" : -13.656855
    },
    "orientation" : 15
  }, {
    "shape" : "7e88e7b3-3737-44bb-8ee6-72e2ff7736b2",
    "color" : "#FF3333",
    "position" : {
      "x" : -32.0,
      "y" : 19.31371,
      "z" : -8.0
    },
    "orientation" : 23
  }, {
    "shape" : "7e88e7b3-3737-44bb-8ee6-72e2ff7736b2",
    "color" : "#3333FF",
    "position" : {
      "x" : 11.313708,
      "y" : 51.31371,
      "z" : -27.31371
    },
    "orientation" : 18
  }, {
    "shape" : "7e88e7b3-3737-44bb-8ee6-72e2ff7736b2",
    "color" : "#3333FF",
    "position" : {
      "x" : 27.31371,
      "y" : 0.0,
      "z" : -59.31371
    },
    "orientation" : 7
  }, {
    "shape" : "7e88e7b3-3737-44bb-8ee6-72e2ff7736b2",
    "color" : "#FF3333",
    "position" : {
      "x" : -32.0,
      "y" : -13.656855,
      "z" : -13.656855
    },
    "orientation" : 23
  }, {
    "shape" : "f8b4c7ca-148d-4a72-9d06-6ad5e5177196",
    "color" : "#FFFF00",
    "position" : {
      "x" : -32.0,
      "y" : 13.656855,
      "z" : -13.656855
    },
    "orientation" : 17
  }, {
    "shape" : "fb1507dd-ee38-4bf9-9c09-b1ecd025d785",
    "color" : "#FFFFFF",
    "position" : {
      "x" : -32.0,
      "y" : -32.0,
      "z" : 32.0
    }
  }, {
    "shape" : "fb1507dd-ee38-4bf9-9c09-b1ecd025d785",
    "color" : "#FFFFFF",
    "position" : {
      "x" : 51.31371,
      "y" : 51.31371,
      "z" : 0.0
    }
  }, {
    "shape" : "fb1507dd-ee38-4bf9-9c09-b1ecd025d785",
    "color" : "#FFFFFF",
    "position" : {
      "x" : 19.31371,
      "y" : 19.31371,
      "z" : -59.31371
    }
  }, {
    "shape" : "7e88e7b3-3737-44bb-8ee6-72e2ff7736b2",
    "color" : "#00CC00",
    "position" : {
      "x" : 5.656854,
      "y" : -13.656855,
      "z" : -59.31371
    },
    "orientation" : 19
  }, {
    "shape" : "fb1507dd-ee38-4bf9-9c09-b1ecd025d785",
    "color" : "#FFFFFF",
    "position" : {
      "x" : 0.0,
      "y" : 0.0,
      "z" : -59.31371
    }
  }, {
    "shape" : "d4858e14-52d5-42eb-a50e-9361c57d7ebd",
    "color" : "#00CC00",
    "position" : {
      "x" : 89.941124,
      "y" : 51.31371,
      "z" : -8.0
    },
    "orientation" : 14
  }, {
    "shape" : "21f47278-1ceb-4c52-b67f-5b959da5e322",
    "color" : "#3333FF",
    "position" : {
      "x" : -32.0,
      "y" : 0.0,
      "z" : 19.31371
    },
    "orientation" : 18
  }, {
    "shape" : "f8b4c7ca-148d-4a72-9d06-6ad5e5177196",
    "color" : "#FFFF00",
    "position" : {
      "x" : -32.0,
      "y" : -13.656855,
      "z" : -13.656855
    },
    "orientation" : 17
  }, {
    "shape" : "fb1507dd-ee38-4bf9-9c09-b1ecd025d785",
    "color" : "#FFFFFF",
    "position" : {
      "x" : 89.941124,
      "y" : 51.31371,
      "z" : 0.0
    }
  }, {
    "shape" : "fb1507dd-ee38-4bf9-9c09-b1ecd025d785",
    "color" : "#FFFFFF",
    "position" : {
      "x" : -32.0,
      "y" : -32.0,
      "z" : -32.0
    }
  }, {
    "shape" : "d4858e14-52d5-42eb-a50e-9361c57d7ebd",
    "color" : "#FF3333",
    "position" : {
      "x" : 70.62742,
      "y" : 51.31371,
      "z" : 5.656854
    },
    "orientation" : 12
  }, {
    "shape" : "7e88e7b3-3737-44bb-8ee6-72e2ff7736b2",
    "color" : "#FFFF00",
    "position" : {
      "x" : 38.62742,
      "y" : 0.0,
      "z" : -59.31371
    },
    "orientation" : 2
  }, {
    "shape" : "21f47278-1ceb-4c52-b67f-5b959da5e322",
    "color" : "#FF3333",
    "position" : {
      "x" : 24.970562,
      "y" : 51.31371,
      "z" : -21.656855
    },
    "orientation" : 0
  }, {
    "shape" : "d4858e14-52d5-42eb-a50e-9361c57d7ebd",
    "color" : "#00CC00",
    "position" : {
      "x" : 51.31371,
      "y" : 51.31371,
      "z" : -8.0
    },
    "orientation" : 0
  }, {
    "shape" : "4c9597d6-30d9-4032-beef-c8b010f6a888",
    "color" : "#FF3333",
    "position" : {
      "x" : 13.656855,
      "y" : 5.656854,
      "z" : 5.656854
    },
    "orientation" : 23
  }, {
    "shape" : "4c9597d6-30d9-4032-beef-c8b010f6a888",
    "color" : "#3333FF",
    "position" : {
      "x" : 19.31371,
      "y" : -19.31371,
      "z" : 0.0
    },
    "orientation" : 7
  } ]
}